bflore/__init__.py
bflore/cli.py
bflore/core.py
bflore/middleware.py
bflore/utils.py
bflore-0.1.0.dist-info/METADATA
bflore-0.1.0.dist-info/WHEEL
bflore-0.1.0.dist-info/entry_points.txt
bflore-0.1.0.dist-info/top_level.txt
bflore-0.1.0.dist-info/RECORD
