Metadata-Version: 2.4
Name: bflore
Version: 0.1.0
Summary: مكتبة لتوسيع إمكانيات Flask مع دعم للروابط المحلية المخصصة
Home-page: https://github.com/yourusername/bflore
Author: Bflore Team
Author-email: contact@example.com
Classifier: Programming Language :: Python :: 3
Classifier: License :: OSI Approved :: MIT License
Classifier: Operating System :: OS Independent
Classifier: Development Status :: 3 - Alpha
Classifier: Framework :: Flask
Classifier: Intended Audience :: Developers
Classifier: Topic :: Software Development :: Libraries :: Application Frameworks
Requires-Python: >=3.6
Requires-Dist: flask>=2.0.0
Requires-Dist: click>=7.0
Dynamic: author
Dynamic: author-email
Dynamic: classifier
Dynamic: description
Dynamic: description-content-type
Dynamic: home-page
Dynamic: requires-dist
Dynamic: requires-python
Dynamic: summary
